gptbioinsightor/__init__.py
gptbioinsightor/celltype.py
gptbioinsightor/constant.py
gptbioinsightor/core.py
gptbioinsightor/exception.py
gptbioinsightor/gsea.py
gptbioinsightor/logging_utils.py
gptbioinsightor/pathway.py
gptbioinsightor/structure.py
gptbioinsightor/utils.py
gptbioinsightor/prompt/__init__.py
gptbioinsightor/prompt/_celltype.py
gptbioinsightor/prompt/_pathway.py
gptbioinsightor-0.7.6.dist-info/METADATA
gptbioinsightor-0.7.6.dist-info/WHEEL
gptbioinsightor-0.7.6.dist-info/licenses/LICENSE
gptbioinsightor-0.7.6.dist-info/RECORD
