Metadata-Version: 2.4
Name: gptbioinsightor
Version: 0.7.6
Summary: GPTBioInsightor utilizes the powerful capabilities of large language models to help people quickly gain knowledge and insight, enhancing their work efficiency.
Project-URL: Homepage, https://github.com/huang-sh/GPTBioInsightor
Project-URL: Repository, https://github.com/huang-sh/GPTBioInsightor
Author-email: Shenghui Huang <hsh-me@outlook.com>
License: BSD 3-Clause
License-File: LICENSE
Requires-Python: >=3.9
Requires-Dist: anthropic>=0.33.0
Requires-Dist: frozendict>=2.4.0
Requires-Dist: gseapy>=1.1.0
Requires-Dist: instructor>=1.7.0
Requires-Dist: litellm==1.57.0
Requires-Dist: openai>=1.31.0
Requires-Dist: perplexityai
Requires-Dist: scanpy>=1.9.0
Provides-Extra: dev
Requires-Dist: pytest>=8.3.3; extra == 'dev'
